{
	"schema_version": 1,
	"quilt_loader": {
		"group": "net.irisfeanora.mods",
		"id": "vanadium",
		"version": "${version}",
		"metadata": {
			"name": "Vanadium",
			"description": "server-side tech tweaking mod",
			"contributors": {
				"ExaInsanity": "Owner"
			},
			"contact": {
				"homepage": "https://github.com/ExaInsanity/vanadium-1.18",
				"issues": "https://github.com/ExaInsanity/vanadium-1.18/issues",
				"sources": "https://github.com/ExaInsanity/vanadium-1.18"
			},
			"icon": "assets/vanadium/icon.png"
		},
		"intermediate_mappings": "net.fabricmc:intermediary",
		"entrypoints": {
			"init": "net.irisfeanora.mods.vanadium.VanadiumMod"
		},
		"depends": [
			{
				"id": "quilt_loader",
				"versions": ">=0.16.0-"
			},
			{
				"id": "minecraft",
				"versions": ">=1.18.2"
			}
		]
	},
	"mixin": "vanadium.mixins.json",
	"accessWidener": "vanadium.accesswidener"
}
